{
    "version": "https://jsonfeed.org/version/1.1",
    "title": "JSON Feed",
    "description": "i.webthings - an independent, noncommercial web initiative.",
    "favicon": "http://localhost:4000/wp-content/uploads/2020/10/cropped-j0920-f-copy-180x180.png",
    "language": "en",
    "home_page_url": "http://localhost:4000/",
    "feed_url": "http://localhost:4000/feed.json",
    "user_comment": "This feed allows you to read the blogs from this site in any feed reader that supports the JSON Feed format.",
    "items": 
    [
        
            {
            "id": "http://localhost:4000",
            "url": "http://localhost:4000/linkylove.webpath-04-03-26/",
            "language": "en",
            "title": "linkylove.webpath 04-03-26",
            "summary": null,
            "content_html": "<ul class=\"linkylove\">\n\t<li><a title=\"lucille a.k.a. luci\" href=\"https://kawaii.nekoweb.org/\">welcome to <small>KAWAII</small>! ☆</a> <span title=\"led to link shown below\">&#8594;</span></li>\n\t<li><a title=\"mocha a.k.a. mimi\" href=\"https://kkul.neocities.org/\">slice of love ♡</a> <span title=\"led to link shown below\">&#8594;</span></li>\n\t<li><a title=\"Robin\" href=\"https://cherrymocha.neocities.org/\">ma chérie</a> <span title=\"led to link shown below\">&#8594;</span></li>\n\t<li><a title=\"Jay\" href=\"https://swirlybearry.neocities.org/\">Jay's Digital Diary</a> <span title=\"led to link shown below\">&#8594;</span></li>\n\t<li><a title=\"andrea a.k.a. andi\" href=\"https://andisarchive.neocities.org/\">Andi's Archive</a> <span title=\"led to link shown below\">&#8594;</span></li>\n\t<li><a title=\"inthemeantime\" href=\"https://inthemeantimewecry.neocities.org/\">in the meantime we cry’s garden</a></li>\n</ul>\n\n<p><a aria-hidden=\"true\" tabindex=\"-1\" href=\"https://brid.gy/publish/mastodon\"></a></p>\n",
            "date_published": "2026-04-03T12:05:15-04:00",
            "image": "",
            "banner_image": "",
            "tags": []
            }
        
    ]
}
